soakdb3_api/__init__.py
soakdb3_api/aiohttp_client.py
soakdb3_api/exceptions.py
soakdb3_api/xce_shim.py
soakdb3_api/databases/__init__.py
soakdb3_api/databases/constants.py
soakdb3_api/databases/database_definition.py
soakdb3_api/databases/table_definitions.py
soakdb3_api/datafaces/__init__.py
soakdb3_api/datafaces/aiohttp.py
soakdb3_api/datafaces/constants.py
soakdb3_api/datafaces/context.py
soakdb3_api/datafaces/datafaces.py
soakdb3_api/models/crystal_well_model.py
soakdb3_cli/__init__.py
soakdb3_cli/main.py
soakdb3_cli/version.py
soakdb3_cli/configurations/default/configuration.yaml
soakdb3_cli/subcommands/__init__.py
soakdb3_cli/subcommands/base.py
soakdb3_cli/subcommands/service.py
soakdb3_lib/__init__.py
soakdb3_lib/__main__.py
soakdb3_lib/_version.py
soakdb3_lib/base_aiohttp.py
soakdb3_lib/envvar.py
soakdb3_lib/typing.py
soakdb3_lib/version.py
soakdb3_lib/datafaces/__init__.py
soakdb3_lib/datafaces/aiohttp.py
soakdb3_lib/datafaces/context.py
soakdb3_lib/datafaces/datafaces.py
soakdb3_lib/datafaces/normsql.py
soakdb3_xls/XsoakDB_v3.0_library.xlsm
soakdb3_xls/__init__.py
soakdb3_xls/excel_config.json
soakdb3_xls/import_export.xlsm
soakdb3_xls/lb19758-64.bat
soakdb3_xls/soakDB3.bat
soakdb3_xls/soakDB_v3.0.xlsm
soakdb3-1.7.1.dist-info/LICENSE
soakdb3-1.7.1.dist-info/METADATA
soakdb3-1.7.1.dist-info/WHEEL
soakdb3-1.7.1.dist-info/entry_points.txt
soakdb3-1.7.1.dist-info/top_level.txt
soakdb3-1.7.1.dist-info/RECORD
